influxdb/__init__.py
influxdb/_dataframe_client.py
influxdb/chunked_json.py
influxdb/client.py
influxdb/dataframe_client.py
influxdb/exceptions.py
influxdb/helper.py
influxdb/line_protocol.py
influxdb/resultset.py
influxdb/influxdb08/__init__.py
influxdb/influxdb08/chunked_json.py
influxdb/influxdb08/client.py
influxdb/influxdb08/dataframe_client.py
influxdb/influxdb08/helper.py
influxdb/tests/__init__.py
influxdb/tests/chunked_json_test.py
influxdb/tests/client_test.py
influxdb/tests/dataframe_client_test.py
influxdb/tests/helper_test.py
influxdb/tests/misc.py
influxdb/tests/resultset_test.py
influxdb/tests/test_line_protocol.py
influxdb/tests/influxdb08/__init__.py
influxdb/tests/influxdb08/client_test.py
influxdb/tests/influxdb08/dataframe_client_test.py
influxdb/tests/influxdb08/helper_test.py
influxdb/tests/server_tests/__init__.py
influxdb/tests/server_tests/base.py
influxdb/tests/server_tests/client_test_with_server.py
influxdb/tests/server_tests/influxdb_instance.py
influxdb-5.3.0.dist-info/LICENSE
influxdb-5.3.0.dist-info/METADATA
influxdb-5.3.0.dist-info/WHEEL
influxdb-5.3.0.dist-info/top_level.txt
influxdb-5.3.0.dist-info/RECORD
